[
	[
		["ŝ","ĝ","e","r","t","ŭ","u","i","o","p","ĵ","ĥ"],
		["a","s","d","f","g","h","j","k","l"],
		[1,"z","ĉ","c","v","b","n","m",8],
		[3,2,","," ","/",".","\n"]
	],
	{
		"1": [".",",","'","?","!","\"","1","-","(",")","@","/",":","_"],
		"2": ["a","b","c","2","ĉ","ä","æ","å","à","á","â","ã","ç"],
		"3": ["d","e","f","3","è","é","ê","ë","ð"],
		"4": ["g","h","i","4","ĝ","ĥ","ì","í","î","ï"],
		"5": ["j","k","l","5","ĵ"],
		"6": ["m","n","o","6","ö","ø","ò","ó","ô","õ","ñ"],
		"7": ["p","q","r","s","7","ŝ","ß","$"],
		"8": ["t","u","v","8","ŭ","ù","ú","û","ü"],
		"9": ["w","x","y","z","9","ý","þ"]
	}
]
